kodoc_tokenizer/__init__.py
kodoc_tokenizer/text_cleaner.py
kodoc_tokenizer/tokenization_kodoc.py
kodoc_tokenizer/version.txt
kodoc_tokenizer/assets/special_tokens_map.json
kodoc_tokenizer/assets/tokenizer_config.json
kodoc_tokenizer/assets/vocab.txt
kodoc_tokenizer/transformers/__init__.py
kodoc_tokenizer/transformers/file_utils.py
kodoc_tokenizer/transformers/tokenization_utils.py
kodoc_tokenizer/transformers/tokenization_utils_base.py
kodoc_tokenizer-0.2.0rc1.dist-info/METADATA
kodoc_tokenizer-0.2.0rc1.dist-info/WHEEL
kodoc_tokenizer-0.2.0rc1.dist-info/top_level.txt
kodoc_tokenizer-0.2.0rc1.dist-info/RECORD
