Metadata-Version: 2.1
Name: kodoc-tokenizer
Version: 0.2.0rc1
Summary: Tokenizer for kodoc
Home-page: https://github.com/kodoc/kodoc-tokenizer
Author: Jangwon Park
Author-email: adieujw@gmail.com
License: Apache License 2.0
Platform: UNKNOWN
Requires-Python: >=3.6
Requires-Dist: numpy
Requires-Dist: packaging
Requires-Dist: dataclasses ; python_version < "3.7"
Requires-Dist: importlib-metadata ; python_version < "3.8"
